LICENSE
MANIFEST.in
README.md
pyproject.toml
setup.py
curve25519/curve25519module.c
curve25519/curve/curve25519-donna.c
curve25519/curve/curve25519-donna.h
curve25519/curve/ed25519/api.h
curve25519/curve/ed25519/base.h
curve25519/curve/ed25519/base2.h
curve25519/curve/ed25519/d.h
curve25519/curve/ed25519/d2.h
curve25519/curve/ed25519/fe.h
curve25519/curve/ed25519/fe_0.c
curve25519/curve/ed25519/fe_1.c
curve25519/curve/ed25519/fe_add.c
curve25519/curve/ed25519/fe_cmov.c
curve25519/curve/ed25519/fe_copy.c
curve25519/curve/ed25519/fe_frombytes.c
curve25519/curve/ed25519/fe_invert.c
curve25519/curve/ed25519/fe_isnegative.c
curve25519/curve/ed25519/fe_isnonzero.c
curve25519/curve/ed25519/fe_mul.c
curve25519/curve/ed25519/fe_neg.c
curve25519/curve/ed25519/fe_pow22523.c
curve25519/curve/ed25519/fe_sq.c
curve25519/curve/ed25519/fe_sq2.c
curve25519/curve/ed25519/fe_sub.c
curve25519/curve/ed25519/fe_tobytes.c
curve25519/curve/ed25519/ge.h
curve25519/curve/ed25519/ge_add.c
curve25519/curve/ed25519/ge_add.h
curve25519/curve/ed25519/ge_double_scalarmult.c
curve25519/curve/ed25519/ge_frombytes.c
curve25519/curve/ed25519/ge_madd.c
curve25519/curve/ed25519/ge_madd.h
curve25519/curve/ed25519/ge_msub.c
curve25519/curve/ed25519/ge_msub.h
curve25519/curve/ed25519/ge_p1p1_to_p2.c
curve25519/curve/ed25519/ge_p1p1_to_p3.c
curve25519/curve/ed25519/ge_p2_0.c
curve25519/curve/ed25519/ge_p2_dbl.c
curve25519/curve/ed25519/ge_p2_dbl.h
curve25519/curve/ed25519/ge_p3_0.c
curve25519/curve/ed25519/ge_p3_dbl.c
curve25519/curve/ed25519/ge_p3_to_cached.c
curve25519/curve/ed25519/ge_p3_to_p2.c
curve25519/curve/ed25519/ge_p3_tobytes.c
curve25519/curve/ed25519/ge_precomp_0.c
curve25519/curve/ed25519/ge_scalarmult_base.c
curve25519/curve/ed25519/ge_sub.c
curve25519/curve/ed25519/ge_sub.h
curve25519/curve/ed25519/ge_tobytes.c
curve25519/curve/ed25519/open.c
curve25519/curve/ed25519/pow22523.h
curve25519/curve/ed25519/pow225521.h
curve25519/curve/ed25519/sc.h
curve25519/curve/ed25519/sc_muladd.c
src/omemo_dr.egg-info/PKG-INFO
src/omemo_dr.egg-info/SOURCES.txt
src/omemo_dr.egg-info/dependency_links.txt
src/omemo_dr.egg-info/requires.txt
src/omemo_dr.egg-info/top_level.txt
