Metadata-Version: 2.4
Name: omemo-dr
Version: 1.2.0
Summary: OMEMO Double Ratchet
Author: Philipp Hörist
Author-email: philipp@hoerist.com
License: GNU GENERAL PUBLIC LICENSE
Classifier: Intended Audience :: Developers
Classifier: License :: OSI Approved :: GNU General Public License v3 (GPLv3)
Classifier: Programming Language :: Python :: 3
Classifier: Topic :: Security :: Cryptography
Classifier: Topic :: Software Development :: Libraries :: Python Modules
Requires-Python: >=3.10
License-File: LICENSE
Requires-Dist: cryptography
Requires-Dist: protobuf>=4.21.0
Provides-Extra: dev
Requires-Dist: ruff>=0.5.4; extra == "dev"
Requires-Dist: codespell[toml]>=2.2.4; extra == "dev"
Requires-Dist: black>=23.1.0; extra == "dev"
Dynamic: license-file
